{
  "project_info": {
    "project_number": "77409035989",
    "firebase_url": "https://find-me-87953.firebaseio.com",
    "project_id": "find-me-87953",
    "storage_bucket": "find-me-87953.appspot.com"
  },
  "client": [
    {
      "client_info": {
        "mobilesdk_app_id": "1:77409035989:android:a261ee409f86cf0358645c",
        "android_client_info": {
          "package_name": "com.empyrealgames.findme"
        }
      },
      "oauth_client": [
        {
          "client_id": "77409035989-5jmgjbitqh4eoa4qmtfscpitd9oil9qa.apps.googleusercontent.com",
          "client_type": 1,
          "android_info": {
            "package_name": "com.empyrealgames.findme",
            "certificate_hash": "1feb7448744c20c5a463ead71e8d59e4efb950d0"
          }
        },
        {
          "client_id": "77409035989-jgqsiv9vkcs351gik229vjvr60meu2d8.apps.googleusercontent.com",
          "client_type": 1,
          "android_info": {
            "package_name": "com.empyrealgames.findme",
            "certificate_hash": "4fdafa551813fc21b855504c06cc0742c1848420"
          }
        },
        {
          "client_id": "77409035989-aan1cbqqb3jfufd9lctm9vsg8jidkqnu.apps.googleusercontent.com",
          "client_type": 3
        }
      ],
      "api_key": [
        {
          "current_key": "AIzaSyCWzq-ngO1ecluKbukq6RGlxgu1PhCcrJs"
        }
      ],
      "services": {
        "appinvite_service": {
          "other_platform_oauth_client": [
            {
              "client_id": "77409035989-aan1cbqqb3jfufd9lctm9vsg8jidkqnu.apps.googleusercontent.com",
              "client_type": 3
            }
          ]
        }
      }
    }
  ],
  "configuration_version": "1"
}